{
  "id": "fxbus",
  "title": "FX Bus",
  "description": "GM-broadcast, client-side visual effects framework. Provides a single socket-based FX listener that renders deterministic, visual-only effects locally on each client using PIXI and canvas.app.ticker. No document mutation. Explicit start/stop semantics with global reset.",
  "version": "0.5.2",
  "authors": [
    {
      "name": "mintchoc"
    }
  ],
  "compatibility": {
    "minimum": "13",
    "verified": "13"
  },
  "esmodules": [
    "scripts/fxbus.js"
  ],
  "styles": [
    "styles/fxbus.css"
  ],
  "socket": true,
  "url": "https://github.com/SamF111/fxbus",
  "readme": "https://github.com/SamF111/fxbus/README.md",
  "bugs": "https://github.com/SamF111/fxbus/issues",
  "changelog": "https://github.com/SamF111/fxbus/releases",
  "license": "LICENSE",
  "manifest": "https://github.com/SamF111/fxbus/releases/latest/download/module.json",
  "download": "https://github.com/SamF111/fxbus/releases/latest/download/fxbus-0.5.1.zip"
}